<featureType>
  <id>FeatureTypeInfoImpl--32165d5a:157b6239e58:-7ff6</id>
  <name>aodn_nsw_oeh_bathy_map</name>
  <nativeName>aodn_nsw_oeh_bathy_map</nativeName>
  <namespace>
    <id>NamespaceInfoImpl-3b0a723a:137e9896802:-7ffd</id>
  </namespace>
  <title>aodn_nsw_oeh_bathy_map</title>
  <keywords>
    <string>features</string>
    <string>aodn_nsw_oeh_bathy_map</string>
  </keywords>
  <nativeCRS>GEOGCS[&quot;WGS 84&quot;, 
  DATUM[&quot;World Geodetic System 1984&quot;, 
    SPHEROID[&quot;WGS 84&quot;, 6378137.0, 298.257223563, AUTHORITY[&quot;EPSG&quot;,&quot;7030&quot;]], 
    AUTHORITY[&quot;EPSG&quot;,&quot;6326&quot;]], 
  PRIMEM[&quot;Greenwich&quot;, 0.0, AUTHORITY[&quot;EPSG&quot;,&quot;8901&quot;]], 
  UNIT[&quot;degree&quot;, 0.017453292519943295], 
  AXIS[&quot;Geodetic longitude&quot;, EAST], 
  AXIS[&quot;Geodetic latitude&quot;, NORTH], 
  AUTHORITY[&quot;EPSG&quot;,&quot;4326&quot;]]</nativeCRS>
  <srs>EPSG:4326</srs>
  <nativeBoundingBox>
    <minx>152.234064105874</minx>
    <maxx>152.992814825859</maxx>
    <miny>-32.6899063037971</miny>
    <maxy>-31.3843963566904</maxy>
    <crs>EPSG:4326</crs>
  </nativeBoundingBox>
  <latLonBoundingBox>
    <minx>152.234064105874</minx>
    <maxx>152.992814825859</maxx>
    <miny>-32.6899063037971</miny>
    <maxy>-31.3843963566904</maxy>
    <crs>GEOGCS[&quot;WGS84(DD)&quot;, 
  DATUM[&quot;WGS84&quot;, 
    SPHEROID[&quot;WGS84&quot;, 6378137.0, 298.257223563]], 
  PRIMEM[&quot;Greenwich&quot;, 0.0], 
  UNIT[&quot;degree&quot;, 0.017453292519943295], 
  AXIS[&quot;Geodetic longitude&quot;, EAST], 
  AXIS[&quot;Geodetic latitude&quot;, NORTH]]</crs>
  </latLonBoundingBox>
  <projectionPolicy>FORCE_DECLARED</projectionPolicy>
  <enabled>true</enabled>
  <metadata>
    <entry key="time">
      <dimensionInfo>
        <enabled>false</enabled>
        <defaultValue/>
      </dimensionInfo>
    </entry>
    <entry key="cachingEnabled">false</entry>
    <entry key="elevation">
      <dimensionInfo>
        <enabled>false</enabled>
      </dimensionInfo>
    </entry>
  </metadata>
  <store class="dataStore">
    <id>DataStoreInfoImpl--32165d5a:157b6239e58:-7ff7</id>
  </store>
  <maxFeatures>0</maxFeatures>
  <numDecimals>0</numDecimals>
  <overridingServiceSRS>false</overridingServiceSRS>
  <skipNumberMatched>false</skipNumberMatched>
  <circularArcPresent>false</circularArcPresent>
</featureType>