<?xml version="1.0"?>
<filters>
  <filter>
    <name>animal_id</name>
    <type>String</type>
    <label>Animal ID</label>
    <visualised>true</visualised>
    <excludedFromDownload>false</excludedFromDownload>
  </filter>
  <filter>
    <name>geom</name>
    <type>Geometry</type>
    <label>geom</label>
    <visualised>true</visualised>
    <excludedFromDownload>false</excludedFromDownload>
  </filter>
  <filter>
    <name>release_date</name>
    <type>Timestamp</type>
    <label>Release date</label>
    <visualised>true</visualised>
    <excludedFromDownload>false</excludedFromDownload>
  </filter>
  <filter>
    <name>release_location</name>
    <type>String</type>
    <label>Release site</label>
    <visualised>true</visualised>
    <excludedFromDownload>false</excludedFromDownload>
  </filter>
  <filter>
    <name>timestamp</name>
    <type>DateRange</type>
    <label>Time</label>
    <visualised>true</visualised>
    <excludedFromDownload>false</excludedFromDownload>
    <wmsStartDateName>start_date</wmsStartDateName>
    <wmsEndDateName>end_date</wmsEndDateName>
  </filter>
</filters>